ebx/__init__.py
ebx/auth.py
ebx/client.py
ebx/config.py
ebx/encoder.py
ebx/utils.py
ebx/constants/api.py
ebx/endpoints/projects.py
ebx/endpoints/runs.py
ebx/endpoints/services.py
ebx/models/__init__.py
ebx/models/auth_token.py
ebx/models/exec_parameters.py
ebx/models/layer.py
ebx/models/oauth_client.py
ebx/models/output.py
ebx/models/project.py
ebx/models/project_spec.py
ebx/models/run.py
ebx/models/variables/__init__.py
ebx/models/variables/area_variable.py
ebx/models/variables/base_variable.py
ebx/models/variables/date_range_variable.py
ebx/models/variables/date_variable.py
ebx/persistence/abstact_persistence.py
ebx/persistence/in_memory.py
ebx/persistence/local_filesystem.py
ebx/typings/areas.py
examples/applications/nbs/ebxapp.py
examples/applications/nbs/components/ebx_figure.py
examples/applications/nbs/components/ebx_map.py
examples/applications/nbs/components/ebx_table.py
examples/applications/nbs/helpers/api.py
examples/applications/nbs/helpers/config.py
examples/applications/nbs/helpers/utils.py
examples/applications/nbs/pages/area.py
examples/applications/nbs/pages/output.py
examples/applications/nbs/pages/upload.py
examples/applications/nbs/partials/dashboard.py
examples/applications/nbs/partials/login.py
examples/applications/nbs/partials/polygon_upload.py
examples/applications/nbs/partials/projects.py
tests/e2e/test_projects.py
tests/e2e/test_runs.py
tests/unit/__init__.py
tests/unit/constants.py
tests/unit/test_auth_basic.py
tests/unit/test_auth_env.py
tests/unit/test_auth_oauth.py
tests/unit/test_endpoints.py
tests/unit/test_model_auth_token.py
tests/unit/test_model_exec_parameters.py
tests/unit/test_model_layer.py
tests/unit/test_model_oauth_client.py
tests/unit/test_model_output.py
tests/unit/test_model_product_spec.py
tests/unit/test_model_project.py
tests/unit/test_model_run.py
tests/unit/test_model_variable_date_range.py
tests/unit/test_model_variables_area.py
tests/unit/test_model_variables_base.py
tests/unit/test_model_variables_date.py
ebx-0.7.3.dist-info/LICENSE
ebx-0.7.3.dist-info/METADATA
ebx-0.7.3.dist-info/WHEEL
ebx-0.7.3.dist-info/top_level.txt
ebx-0.7.3.dist-info/RECORD
